setup.py
weightbot/__init__.py
weightbot/api.py
weightbot.egg-info/PKG-INFO
weightbot.egg-info/SOURCES.txt
weightbot.egg-info/dependency_links.txt
weightbot.egg-info/not-zip-safe
weightbot.egg-info/requires.txt
weightbot.egg-info/top_level.txt