Metadata-Version: 1.0
Name: weightbot
Version: 0.1
Summary: An unofficial API into WeightBot.com
Home-page: http://github.com/ericflo/weightbot/tree/master
Author: Eric Florenzano
Author-email: floguy@gmail.com
License: BSD
Keywords: weight,weightbot,api
Platform: UNKNOWN
Classifier: Programming Language :: Python
Classifier: Topic :: Software Development :: Libraries :: Python Modules
Classifier: Environment :: Web Environment
